envoy/code_format/python_check/__init__.py
envoy/code_format/python_check/abstract.py
envoy/code_format/python_check/checker.py
envoy/code_format/python_check/cmd.py
envoy/code_format/python_check/py.typed
envoy.code_format.python_check-0.0.8.dist-info/METADATA
envoy.code_format.python_check-0.0.8.dist-info/WHEEL
envoy.code_format.python_check-0.0.8.dist-info/entry_points.txt
envoy.code_format.python_check-0.0.8.dist-info/namespace_packages.txt
envoy.code_format.python_check-0.0.8.dist-info/top_level.txt
envoy.code_format.python_check-0.0.8.dist-info/RECORD
