Metadata-Version: 2.1
Name: envoy.code-format.python-check
Version: 0.0.8
Summary: "Python code format linter/checker used in Envoy proxy's CI"
Home-page: https://github.com/envoyproxy/pytooling/tree/main/envoy.code_format.python_check
Author: Ryan Northey
Author-email: ryan@synca.io
Maintainer: Ryan Northey
Maintainer-email: ryan@synca.io
License: Apache Software License 2.0
Platform: UNKNOWN
Requires-Dist: abstracts (>=0.0.12)
Requires-Dist: aio.core (>=0.3.0)
Requires-Dist: aio.run.checker (>=0.2.1)
Requires-Dist: flake8
Requires-Dist: yapf
